standalone/__init__.py
standalone/config.py
standalone/conversation.py
standalone/main.py
standalone/memory.py
standalone/retriever.py
standalone_naman1607vyas/__init__.py
standalone_naman1607vyas/config.py
standalone_naman1607vyas/conversation.py
standalone_naman1607vyas/main.py
standalone_naman1607vyas/memory.py
standalone_naman1607vyas/retriever.py
tests/__init__.py
tests/test_main.py
standalone_naman1607vyas-0.1.dist-info/METADATA
standalone_naman1607vyas-0.1.dist-info/WHEEL
standalone_naman1607vyas-0.1.dist-info/entry_points.txt
standalone_naman1607vyas-0.1.dist-info/top_level.txt
standalone_naman1607vyas-0.1.dist-info/RECORD
