Metadata-Version: 2.1
Name: standalone-naman1607vyas
Version: 0.1
Requires-Dist: langchain
Requires-Dist: openai
Requires-Dist: sentence-transformers
Requires-Dist: faiss-cpu
Requires-Dist: datasets
Requires-Dist: numpy
